Workbook

Sheet Summary
A1: Topic | B1: Details
A2: Workbook Purpose | B2: Draft trial balance variance analysis and follow-up question aid for human review.
A3: Input Files | B3: FY25 TB.csv; FY26 TB.csv
A4: Thresholds Used | B4: Question triggered only when absolute dollar change is at least $200,000 AND absolute percent change is at least 20%.
A5: Balance Convention | B5: Single signed balance column preserved; parenthetical currency values treated as negative.
A6: Prior-Year Rows / Total | B6: 247 rows; total $-1.00
A7: Current-Year Rows / Total | B7: 247 rows; total $-5.00
A8: Comparison Rows | B8: 246
A9: Questions Generated | B9: 8
A10: Prior-Year Mappings | B10: {"account_category": "Category", "account_name": "Account Name", "account_number": "Account Number", "balance": "Balance", "department": "Department"}
A11: Current-Year Mappings | B11: {"account_category": "Category", "account_name": "Account Name", "account_number": "Account Number", "balance": "Balance", "department": "Department"}
A12: Duplicate Aggregation | B12: Prior-year duplicate match keys: 1; current-year duplicate match keys: 1.
A13: Validation Status | B13: Completed with limitations. Both input files loaded successfully; Account name and balance columns identified per file; All balances are numeric; Comparison row count equals unique match keys across both years; Dollar change equals current year balance less prior year balance; Suggested questions populated only for triggered rows; AND threshold logic applied consistently; No Materiality Score column generated; Summary documents thresholds, mappings, aggregation counts, and balance convention
A14: Human Review Needed | B14: Review generated questions, account classifications, balance-sign conventions, and any accounts near but below the configured thresholds.
A15: Limitations | B15: Outputs are review aids and draft workpapers only; they do not establish final audit, compliance, financial, or management conclusions.

Sheet Prior_Year_TB
A1: match_key | B1: Account Number | C1: Account Name | D1: Account Category | E1: Department | F1: Balance | G1: Source File | H1: Source Year
A2: 1000 | B2: 1000 | C2: Accumulated Depreciation - Admin | D2: Assets | E2: Admin | F2: -62867 | G2: FY25 TB.csv | H2: Prior Year
A3: 1010 | B3: 1010 | C3: Fixed Assets - IT | D3: Assets | E3: IT | F3: 36660 | G3: FY25 TB.csv | H3: Prior Year
A4: 1021 | B4: 1021 | C4: Fixed Assets - IT | D4: Assets | E4: IT | F4: 32186 | G4: FY25 TB.csv | H4: Prior Year
A5: 1031 | B5: 1031 | C5: Inventory - Ops | D5: Assets | E5: Ops | F5: 118459 | G5: FY25 TB.csv | H5: Prior Year
A6: 1043 | B6: 1043 | C6: Cash - Corporate | D6: Assets | E6: Corporate | F6: 366508 | G6: FY25 TB.csv | H6: Prior Year
A7: 1052 | B7: 1052 | C7: Accumulated Depreciation - Warehouse | D7: Assets | E7: Warehouse | F7: -56907 | G7: FY25 TB.csv | H7: Prior Year
A8: 1061 | B8: 1061 | C8: Inventory - Admin | D8: Assets | E8: Admin | F8: 100134 | G8: FY25 TB.csv | H8: Prior Year
A9: 1072 | B9: 1072 | C9: Accounts Receivable - Sales | D9: Assets | E9: Sales | F9: 18401 | G9: FY25 TB.csv | H9: Prior Year
A10: 1081 | B10: 1081 | C10: Accumulated Depreciation - Ops | D10: Assets | E10: Ops | F10: -33234 | G10: FY25 TB.csv | H10: Prior Year
A11: 1090 | B11: 1090 | C11: Cash - Ops | D11: Assets | E11: Ops | F11: 87019 | G11: FY25 TB.csv | H11: Prior Year
A12: 1103 | B12: 1103 | C12: Accounts Receivable - Corporate | D12: Assets | E12: Corporate | F12: 4468 | G12: FY25 TB.csv | H12: Prior Year
A13: 1114 | B13: 1114 | C13: Accounts Receivable - Corporate | D13: Assets | E13: Corporate | F13: 47302 | G13: FY25 TB.csv | H13: Prior Year
... A248: 7110 | B248: 7110 | C248: Interest Expense - Corporate | D248: Other Expense | E248: Corporate | F248: 22000 | G248: FY25 TB.csv | H248: Prior Year

Sheet Current_Year_TB
A1: match_key | B1: Account Number | C1: Account Name | D1: Account Category | E1: Department | F1: Balance | G1: Source File | H1: Source Year
A2: 1000 | B2: 1000 | C2: Accumulated Depreciation - Admin | D2: Assets | E2: Admin | F2: -78173 | G2: FY26 TB.csv | H2: Current Year
A3: 1010 | B3: 1010 | C3: Fixed Assets - IT | D3: Assets | E3: IT | F3: 29855 | G3: FY26 TB.csv | H3: Current Year
A4: 1021 | B4: 1021 | C4: Fixed Assets - IT | D4: Assets | E4: IT | F4: 28902 | G4: FY26 TB.csv | H4: Current Year
A5: 1031 | B5: 1031 | C5: Inventory - Ops | D5: Assets | E5: Ops | F5: 160013 | G5: FY26 TB.csv | H5: Current Year
A6: 1043 | B6: 1043 | C6: Cash - Corporate | D6: Assets | E6: Corporate | F6: 365140 | G6: FY26 TB.csv | H6: Current Year
A7: 1052 | B7: 1052 | C7: Accumulated Depreciation - Warehouse | D7: Assets | E7: Warehouse | F7: -51123 | G7: FY26 TB.csv | H7: Current Year
A8: 1061 | B8: 1061 | C8: Inventory - Admin | D8: Assets | E8: Admin | F8: 99460 | G8: FY26 TB.csv | H8: Current Year
A9: 1072 | B9: 1072 | C9: Accounts Receivable - Sales | D9: Assets | E9: Sales | F9: 20621 | G9: FY26 TB.csv | H9: Current Year
A10: 1081 | B10: 1081 | C10: Accumulated Depreciation - Ops | D10: Assets | E10: Ops | F10: -31634 | G10: FY26 TB.csv | H10: Current Year
A11: 1090 | B11: 1090 | C11: Cash - Ops | D11: Assets | E11: Ops | F11: 100381 | G11: FY26 TB.csv | H11: Current Year
A12: 1103 | B12: 1103 | C12: Accounts Receivable - Corporate | D12: Assets | E12: Corporate | F12: 4748 | G12: FY26 TB.csv | H12: Current Year
A13: 1114 | B13: 1114 | C13: Accounts Receivable - Corporate | D13: Assets | E13: Corporate | F13: 48576 | G13: FY26 TB.csv | H13: Current Year
... A248: 7110 | B248: 7110 | C248: Interest Expense - Corporate | D248: Other Expense | E248: Corporate | F248: 116000 | G248: FY26 TB.csv | H248: Current Year

Sheet Comparison
A1: match_key | B1: Rank | C1: Account Number | D1: Account Name | E1: Account Category | F1: Department | G1: Prior Year Balance | H1: Current Year Balance | I1: Dollar Change | J1: Percent Change | K1: Change Direction | L1: Question Triggered | M1: Question Trigger Reason | N1: Suggested Client Questions | O1: Analysis Notes
A2: 4010 | B2: 1 | C2: 4010 | D2: Product Revenue - Sales | E2: Revenue | F2: Sales | G2: =SUMIF(Prior_Year_TB!A:A,A2,Prior_Year_TB!F:F) | H2: =SUMIF(Current_Year_TB!A:A,A2,Current_Year_TB!F:F) | I2: =H2-G2 | J2: =IFERROR(I2/ABS(G2),"") | K2: Decrease | L2: Yes | M2: Dollar and percent thresholds met | N2: What changes in volume, pricing, customers, contracts, cutoff, or reclassification explain this revenue variance? | O2: Current-year balance decreased by $630,000 compared with prior year.
A3: 1420 | B3: 2 | C3: 1420 | D3: Inventory - Warehouse | E3: Assets | F3: Warehouse | G3: =SUMIF(Prior_Year_TB!A:A,A3,Prior_Year_TB!F:F) | H3: =SUMIF(Current_Year_TB!A:A,A3,Current_Year_TB!F:F) | I3: =H3-G3 | J3: =IFERROR(I3/ABS(G3),"") | K3: Increase | L3: Yes | M3: Dollar and percent thresholds met | N3: What purchase volume, count adjustment, costing, obsolescence, or write-down activity explains this inventory variance? | O3: Current-year balance increased by $340,000 compared with prior year.
A4: 3053 | B4: 3 | C4: 3053 | D4: Common Stock - IT | E4: Equity | F4: IT | G4: =SUMIF(Prior_Year_TB!A:A,A4,Prior_Year_TB!F:F) | H4: =SUMIF(Current_Year_TB!A:A,A4,Current_Year_TB!F:F) | I4: =H4-G4 | J4: =IFERROR(I4/ABS(G4),"") | K4: Decrease | L4: Yes | M4: Dollar and percent thresholds met | N4: This account changed materially. What underlying activity, timing, cutoff, settlement, or reclassification explains the variance? | O4: Current-year balance decreased by $332,777 compared with prior year.
A5: 1210 | B5: 4 | C5: 1210 | D5: Accounts Receivable - Sales | E5: Assets | F5: Sales | G5: =SUMIF(Prior_Year_TB!A:A,A5,Prior_Year_TB!F:F) | H5: =SUMIF(Current_Year_TB!A:A,A5,Current_Year_TB!F:F) | I5: =H5-G5 | J5: =IFERROR(I5/ABS(G5),"") | K5: Increase | L5: Yes | M5: Dollar and percent thresholds met | N5: What changes in volume, pricing, customers, contracts, cutoff, or reclassification explain this revenue variance? | O5: Current-year balance increased by $300,000 compared with prior year.
A6: 2110 | B6: 5 | C6: 2110 | D6: Accounts Payable - Ops | E6: Liabilities | F6: Ops | G6: =SUMIF(Prior_Year_TB!A:A,A6,Prior_Year_TB!F:F) | H6: =SUMIF(Current_Year_TB!A:A,A6,Current_Year_TB!F:F) | I6: =H6-G6 | J6: =IFERROR(I6/ABS(G6),"") | K6: Decrease | L6: Yes | M6: Dollar and percent thresholds met | N6: What vendor timing, unrecorded liability, reversal, new obligation, cutoff, or reclassification activity explains this payable or accrual variance? | O6: Current-year balance decreased by $290,000 compared with prior year.
A7: 3161 | B7: 6 | C7: 3161 | D7: Retained Earnings - IT | E7: Equity | F7: IT | G7: =SUMIF(Prior_Year_TB!A:A,A7,Prior_Year_TB!F:F) | H7: =SUMIF(Current_Year_TB!A:A,A7,Current_Year_TB!F:F) | I7: =H7-G7 | J7: =IFERROR(I7/ABS(G7),"") | K7: Decrease | L7: Yes | M7: Dollar and percent thresholds met | N7: What contributions, distributions, retained earnings activity, or closing entries explain this equity variance? | O7: Current-year balance decreased by $252,765 compared with prior year.
A8: 2360 | B8: 7 | C8: 2360 | D8: Deferred Revenue - Sales | E8: Liabilities | F8: Sales | G8: =SUMIF(Prior_Year_TB!A:A,A8,Prior_Year_TB!F:F) | H8: =SUMIF(Current_Year_TB!A:A,A8,Current_Year_TB!F:F) | I8: =H8-G8 | J8: =IFERROR(I8/ABS(G8),"") | K8: Decrease | L8: Yes | M8: Dollar and percent thresholds met | N8: What changes in volume, pricing, customers, contracts, cutoff, or reclassification explain this revenue variance? | O8: Current-year balance decreased by $220,000 compared with prior year.
A9: 6120 | B9: 8 | C9: 6120 | D9: Professional Fees - Corporate | E9: Operating Expenses | F9: Corporate | G9: =SUMIF(Prior_Year_TB!A:A,A9,Prior_Year_TB!F:F) | H9: =SUMIF(Current_Year_TB!A:A,A9,Current_Year_TB!F:F) | I9: =H9-G9 | J9: =IFERROR(I9/ABS(G9),"") | K9: Increase | L9: Yes | M9: Dollar and percent thresholds met | N9: What new vendors, one-time projects, renewals, implementation work, timing, or reclassifications explain this operating expense variance? | O9: Current-year balance increased by $201,000 compared with prior year.
A10: 4120 | B10: 9 | C10: 4120 | D10: Discounts - Ops | E10: Revenue | F10: Ops | G10: =SUMIF(Prior_Year_TB!A:A,A10,Prior_Year_TB!F:F) | H10: =SUMIF(Current_Year_TB!A:A,A10,Current_Year_TB!F:F) | I10: =H10-G10 | J10: =IFERROR(I10/ABS(G10),"") | K10: Increase | L10: No | O10: Current-year balance increased by $159,807 compared with prior year.
A11: 1030 | B11: 10 | C11: 1030 | D11: Cash - Corporate | E11: Assets | F11: Corporate | G11: =SUMIF(Prior_Year_TB!A:A,A11,Prior_Year_TB!F:F) | H11: =SUMIF(Current_Year_TB!A:A,A11,Current_Year_TB!F:F) | I11: =H11-G11 | J11: =IFERROR(I11/ABS(G11),"") | K11: Decrease | L11: No | O11: Current-year balance decreased by $143,000 compared with prior year.
A12: 3005 | B12: 11 | C12: 3005 | D12: Distributions - IT | E12: Equity | F12: IT | G12: =SUMIF(Prior_Year_TB!A:A,A12,Prior_Year_TB!F:F) | H12: =SUMIF(Current_Year_TB!A:A,A12,Current_Year_TB!F:F) | I12: =H12-G12 | J12: =IFERROR(I12/ABS(G12),"") | K12: Decrease | L12: No | O12: Current-year balance decreased by $138,048 compared with prior year.
A13: 5220 | B13: 12 | C13: 5220 | D13: Freight In - Warehouse | E13: COGS | F13: Warehouse | G13: =SUMIF(Prior_Year_TB!A:A,A13,Prior_Year_TB!F:F) | H13: =SUMIF(Current_Year_TB!A:A,A13,Current_Year_TB!F:F) | I13: =H13-G13 | J13: =IFERROR(I13/ABS(G13),"") | K13: Increase | L13: No | O13: Current-year balance increased by $129,000 compared with prior year.
A14: 3092 | B14: 13 | C14: 3092 | D14: Current Year Earnings - IT | E14: Equity | F14: IT | G14: =SUMIF(Prior_Year_TB!A:A,A14,Prior_Year_TB!F:F) | H14: =SUMIF(Current_Year_TB!A:A,A14,Current_Year_TB!F:F) | I14: =H14-G14 | J14: =IFERROR(I14/ABS(G14),"") | K14: Increase | L14: No | O14: Current-year balance increased by $123,566 compared with prior year.
A15: 6330 | B15: 14 | C15: 6330 | D15: Software - IT | E15: Operating Expenses | F15: IT | G15: =SUMIF(Prior_Year_TB!A:A,A15,Prior_Year_TB!F:F) | H15: =SUMIF(Current_Year_TB!A:A,A15,Current_Year_TB!F:F) | I15: =H15-G15 | J15: =IFERROR(I15/ABS(G15),"") | K15: Increase | L15: No | O15: Current-year balance increased by $114,000 compared with prior year.
A16: 7110 | B16: 15 | C16: 7110 | D16: Interest Expense - Corporate | E16: Other Expense | F16: Corporate | G16: =SUMIF(Prior_Year_TB!A:A,A16,Prior_Year_TB!F:F) | H16: =SUMIF(Current_Year_TB!A:A,A16,Current_Year_TB!F:F) | I16: =H16-G16 | J16: =IFERROR(I16/ABS(G16),"") | K16: Increase | L16: No | O16: Current-year balance increased by $94,000 compared with prior year.
A17: 3145 | B17: 16 | C17: 3145 | D17: Current Year Earnings - Warehouse | E17: Equity | F17: Warehouse | G17: =SUMIF(Prior_Year_TB!A:A,A17,Prior_Year_TB!F:F) | H17: =SUMIF(Current_Year_TB!A:A,A17,Current_Year_TB!F:F) | I17: =H17-G17 | J17: =IFERROR(I17/ABS(G17),"") | K17: Decrease | L17: No | O17: Current-year balance decreased by $86,852 compared with prior year.
A18: 6420 | B18: 17 | C18: 6420 | D18: Travel - Sales | E18: Operating Expenses | F18: Sales | G18: =SUMIF(Prior_Year_TB!A:A,A18,Prior_Year_TB!F:F) | H18: =SUMIF(Current_Year_TB!A:A,A18,Current_Year_TB!F:F) | I18: =H18-G18 | J18: =IFERROR(I18/ABS(G18),"") | K18: Increase | L18: No | O18: Current-year balance increased by $79,000 compared with prior year.
A19: 7035 | B19: 18 | C19: 7035 | D19: Bank Fees - Ops | E19: Other Expense | F19: Ops | G19: =SUMIF(Prior_Year_TB!A:A,A19,Prior_Year_TB!F:F) | H19: =SUMIF(Current_Year_TB!A:A,A19,Current_Year_TB!F:F) | I19: =H19-G19 | J19: =IFERROR(I19/ABS(G19),"") | K19: Increase | L19: No | O19: Current-year balance increased by $62,206 compared with prior year.
A20: 7185 | B20: 19 | C20: 7185 | D20: Miscellaneous Expense - Sales | E20: Other Expense | F20: Sales | G20: =SUMIF(Prior_Year_TB!A:A,A20,Prior_Year_TB!F:F) | H20: =SUMIF(Current_Year_TB!A:A,A20,Current_Year_TB!F:F) | I20: =H20-G20 | J20: =IFERROR(I20/ABS(G20),"") | K20: Increase | L20: No | O20: Current-year balance increased by $52,720 compared with prior year.
A21: 3203 | B21: 20 | C21: 3203 | D21: Retained Earnings - Ops | E21: Equity | F21: Ops | G21: =SUMIF(Prior_Year_TB!A:A,A21,Prior_Year_TB!F:F) | H21: =SUMIF(Current_Year_TB!A:A,A21,Current_Year_TB!F:F) | I21: =H21-G21 | J21: =IFERROR(I21/ABS(G21),"") | K21: Decrease | L21: No | O21: Current-year balance decreased by $45,202 compared with prior year.
... A247: 1231 | B247: 246 | C247: 1231 | D247: Prepaid Expense - IT | E247: Assets | F247: IT | G247: =SUMIF(Prior_Year_TB!A:A,A247,Prior_Year_TB!F:F) | H247: =SUMIF(Current_Year_TB!A:A,A247,Current_Year_TB!F:F) | I247: =H247-G247 | J247: =IFERROR(I247/ABS(G247),"") | K247: Increase | L247: No | O247: Current-year balance increased by $17 compared with prior year.
